tami4edge_api_client/__init__.py
tami4edge_api_client/client.py
tami4edge_api_client/model.py
tami4edge_api_client-0.2.0.dist-info/METADATA
tami4edge_api_client-0.2.0.dist-info/WHEEL
tami4edge_api_client-0.2.0.dist-info/top_level.txt
tami4edge_api_client-0.2.0.dist-info/RECORD
