Metadata-Version: 2.1
Name: tami4edge-api-client
Version: 0.2.0
Summary: API Client for Tami 4 Edge Cloud
Author: Oren Sadeh
Project-URL: Homepage, https://github.com/osadeh/tami4edge-api-client
Project-URL: Bug Tracker, https://github.com/osadeh/tami4edge-api-client/issues
Classifier: Programming Language :: Python :: 3
Classifier: License :: OSI Approved :: MIT License
Classifier: Operating System :: OS Independent
Requires-Python: >=3.7
